xotl/tools/__init__.py
xotl/tools/_version.py
xotl/tools/bases.py
xotl/tools/bound.py
xotl/tools/clipping.py
xotl/tools/context.py
xotl/tools/context.pyi
xotl/tools/cpystack.py
xotl/tools/crypto.py
xotl/tools/infinity.py
xotl/tools/keywords.py
xotl/tools/modules.py
xotl/tools/names.py
xotl/tools/objects.py
xotl/tools/objects.pyi
xotl/tools/params.py
xotl/tools/py.typed
xotl/tools/records.py
xotl/tools/string.py
xotl/tools/symbols.py
xotl/tools/cli/__init__.py
xotl/tools/cli/app.py
xotl/tools/cli/tools.py
xotl/tools/decorator/__init__.py
xotl/tools/decorator/meta.py
xotl/tools/dim/__init__.py
xotl/tools/dim/base.py
xotl/tools/dim/base.pyi
xotl/tools/dim/currencies.py
xotl/tools/dim/meta.py
xotl/tools/fp/__init__.py
xotl/tools/fp/iterators.py
xotl/tools/fp/iterators.pyi
xotl/tools/fp/option.py
xotl/tools/fp/tools.py
xotl/tools/fp/tools.pyi
xotl/tools/fp/prove/__init__.py
xotl/tools/fp/prove/semantic.py
xotl/tools/fs/__init__.py
xotl/tools/fs/path.py
xotl/tools/future/__init__.py
xotl/tools/future/calendar.py
xotl/tools/future/codecs.py
xotl/tools/future/collections.py
xotl/tools/future/csv.py
xotl/tools/future/datetime.py
xotl/tools/future/datetime.pyi
xotl/tools/future/functools.py
xotl/tools/future/inspect.py
xotl/tools/future/itertools.py
xotl/tools/future/mimetypes.py
xotl/tools/future/pprint.py
xotl/tools/future/subprocess.py
xotl/tools/future/textwrap.py
xotl/tools/future/threading.py
xotl/tools/future/types.py
xotl/tools/tasking/__init__.py
xotl/tools/tasking/_greenlet_local.py
xotl/tools/tasking/lock.py
xotl/tools/tasking/safe.py
xotl/tools/testing/__init__.py
xotl/tools/testing/capture.py
xotl/tools/testing/datetime.py
xotl/tools/testing/unit.py
xotl/tools/testing/staticchecks/check_objects.py
xotl/tools/validators/__init__.py
xotl/tools/validators/identifiers.py
xotl/tools/values/__init__.py
xotl/tools/values/ids.py
xotl/tools/values/simple.py
xotl_tools-3.3.0.dist-info/METADATA
xotl_tools-3.3.0.dist-info/WHEEL
xotl_tools-3.3.0.dist-info/licenses/LICENSE
xotl_tools-3.3.0.dist-info/RECORD
