Metadata-Version: 2.4
Name: xotl.tools
Version: 3.3.0
Summary: Collection of usefull algorithms and other very disparate stuff
Author-email: Merchise Autrement <info@merchise.de>
License-Expression: MIT
License-File: LICENSE
Classifier: Development Status :: 5 - Production/Stable
Classifier: Intended Audience :: Developers
Classifier: Operating System :: POSIX :: Linux
Classifier: Programming Language :: Python
Classifier: Programming Language :: Python :: 3.8
Classifier: Programming Language :: Python :: 3.9
Classifier: Programming Language :: Python :: 3.10
Classifier: Programming Language :: Python :: 3.11
Classifier: Topic :: Software Development :: Libraries :: Python Modules
Requires-Python: >=3.8
Requires-Dist: graphlib-backport; python_version < '3.9'
Requires-Dist: packaging>=23.2
Requires-Dist: typing-extensions>=3.10.0
